<?xml version="1.0" encoding="UTF-8" standalone="no"?>
<catalog prefer="public" xmlns="urn:oasis:names:tc:entity:xmlns:xml:catalog">
    <group id="Folder Repository, directory=, recursive=true, Auto-Update=false, version=2" prefer="public" xml:base="">
        <uri name="https://w3id.org/emmo/1.0.3/emmo" uri="../emmo.ttl"/>
        <uri name="https://w3id.org/emmo/1.0.3/disciplines" uri="../disciplines/disciplines.ttl"/>
        <uri name="https://w3id.org/emmo/1.0.3/reference" uri="../reference/reference.ttl"/>
        <uri name="https://w3id.org/emmo/1.0.3/perspectives" uri="perspectives.ttl"/>
        <uri name="https://w3id.org/emmo/1.0.3/perspectives/contrast" uri="contrast.ttl"/>
        <uri name="https://w3id.org/emmo/1.0.3/perspectives/perspective" uri="perspective.ttl"/>
        <uri name="https://w3id.org/emmo/1.0.3/foundation/mereocausality" uri="../foundation/mereocausality.ttl"/>
        <uri name="https://w3id.org/emmo/1.0.3/contributors" uri="../contributors.ttl"/>
        <uri name="https://w3id.org/emmo/1.0.3/perspectives/holistic" uri="holistic.ttl"/>
        <uri name="https://w3id.org/emmo/1.0.3/perspectives/persistence" uri="persistence.ttl"/>
        <uri name="https://w3id.org/emmo/1.0.3/perspectives/reductionistic" uri="reductionistic.ttl"/>
        <uri name="https://w3id.org/emmo/1.0.3/perspectives/semiotics" uri="semiotics.ttl"/>
        <uri name="https://w3id.org/emmo/1.0.3/perspectives/structural" uri="structural.ttl"/>
        <uri name="https://w3id.org/emmo/1.0.3/reference/information" uri="../reference/information.ttl"/>
        <uri name="https://w3id.org/emmo/1.0.3/reference/data" uri="../reference/data.ttl"/>
        <uri name="https://w3id.org/emmo/1.0.3/reference/persholistic" uri="../reference/persholistic.ttl"/>
        <uri name="https://w3id.org/emmo/1.0.3/reference/physicalistic" uri="../reference/physicalistic.ttl"/>
        <uri name="https://w3id.org/emmo/1.0.3/reference/standardmodel" uri="../reference/standardmodel.ttl"/>
        <uri name="https://w3id.org/emmo/1.0.3/reference/symbolic" uri="../reference/symbolic.ttl"/>
        <uri name="https://w3id.org/emmo/1.0.3/reference/workflow" uri="../reference/workflow.ttl"/>
        <uri name="https://w3id.org/emmo/1.0.3/reference/agency" uri="../reference/agency.ttl"/>
        <uri name="https://w3id.org/emmo/1.0.3/disciplines/chemistry" uri="../disciplines/chemistry.ttl"/>
        <uri name="https://w3id.org/emmo/1.0.3/disciplines/isq" uri="../disciplines/isq.ttl"/>
        <uri name="https://w3id.org/emmo/1.0.3/disciplines/materials" uri="../disciplines/materials.ttl"/>
        <uri name="https://w3id.org/emmo/1.0.3/disciplines/units/sidimensionalunits" uri="../disciplines/units/sidimensionalunits.ttl"/>
        <uri name="https://w3id.org/emmo/1.0.3/disciplines/metrology" uri="../disciplines/metrology.ttl"/>
        <uri name="https://w3id.org/emmo/1.0.3/disciplines/math" uri="../disciplines/math.ttl"/>
        <uri name="https://w3id.org/emmo/1.0.3/disciplines/properties" uri="../disciplines/properties.ttl"/>
        <uri name="https://w3id.org/emmo/1.0.3/disciplines/perceptual" uri="../disciplines/perceptual.ttl"/>
        <uri name="https://w3id.org/emmo/1.0.3/disciplines/computerscience" uri="../disciplines/computerscience.ttl"/>
        <uri name="https://w3id.org/emmo/1.0.3/disciplines/manufacturing" uri="../disciplines/manufacturing.ttl"/>
        <uri name="https://w3id.org/emmo/1.0.3/disciplines/models" uri="../disciplines/models.ttl"/>
        <uri name="https://w3id.org/emmo/1.0.3/disciplines/periodictable" uri="../disciplines/periodictable.ttl"/>
        <uri name="https://w3id.org/emmo/1.0.3/disciplines/geometrical" uri="../disciplines/geometrical.ttl"/>
        <uri name="https://w3id.org/emmo/1.0.3/disciplines/sisystem" uri="../disciplines/sisystem.ttl"/>
        <uri name="https://w3id.org/emmo/1.0.3/disciplines/units/coherentsiunits" uri="../disciplines/units/coherentsiunits.ttl"/>
        <uri name="https://w3id.org/emmo/1.0.3/disciplines/units/siunits" uri="../disciplines/units/siunits.ttl"/>
        <uri name="https://w3id.org/emmo/1.0.3/disciplines/units/noncoherentsiunits" uri="../disciplines/units/noncoherentsiunits.ttl"/>
        <uri name="https://w3id.org/emmo/1.0.3/disciplines/units/prefixedsiunits" uri="../disciplines/units/prefixedsiunits.ttl"/>
        <uri name="https://w3id.org/emmo/1.0.3/disciplines/units/siacceptedspecialunits" uri="../disciplines/units/siacceptedspecialunits.ttl"/>
        <uri name="https://w3id.org/emmo/1.0.3/contributors-mappings" uri="../contributors-mappings.ttl"/>
    </group>
</catalog>
